log2file/__init__.py
log2file/logger.py
log2file/singleton.py
log2file-1.0.dist-info/LICENSE
log2file-1.0.dist-info/METADATA
log2file-1.0.dist-info/WHEEL
log2file-1.0.dist-info/top_level.txt
log2file-1.0.dist-info/RECORD
