Metadata-Version: 2.1
Name: log2file
Version: 1.0
Summary: A python logging wrapper
Home-page: https://github.com/dwSun/pylog2file
Author: dwSun
Author-email: 
License: UNKNOWN
Platform: UNKNOWN
Classifier: Programming Language :: Python :: 3
Classifier: License :: OSI Approved :: MIT License
Classifier: Operating System :: OS Independent
License-File: LICENSE
